arate_limit/__init__.py
arate_limit/py.typed
arate_limit-1.2.1.dist-info/WHEEL
arate_limit-1.2.1.dist-info/METADATA
arate_limit-1.2.1.dist-info/RECORD
